{
  "id": 17392,
  "key": "e",
  "difficulty": "1",
  "md5": null,
  "answer": "Oh, definitely! When I was a kid, one of my favorite places was this little park near my house. It was a small neighborhood spot, but to me, it felt like a world of adventure. There were these towering trees that provided the perfect shade on hot summer days, and I can still remember how the sunlight filtered through the leaves, creating these cool patterns on the ground.\n\nYou know, my friends and I used to spend hours there, riding our bikes, climbing trees, and playing tag. It was like our own little kingdom. There was this swingset that, honestly, felt like flying whenever I swung so high. And then, of course, there was this old wooden bridge over a tiny creek. We would always pretend we were explorers crossing into uncharted territory.\n\nBut what really made it special was the laughter and the memories we created there. It was a place where worries just melted away. Looking back, I think it shaped a lot of who I am today. So, yeah, that little park is definitely a cherished spot from my childhood!",
  "title": "Tell me about a place you loved when you were young.",
  "extData": "{\"pronuncFile\":\"/20250225/10fd106187a84fde8ff6d449a5a93437.mp3\",\"answerTemplate\":\"开场陈述：  \\n“One of the places I loved most during my childhood was [name of the place, e.g., a park, a beach, or a family home].”\\n\\n正文：  \\n关于这个地方的描述：  \\n“I have vivid memories of this place because [reason, such as its beauty, the fun activities, or special significance].”  \\n提及具体细节：  \\n“I remember [describe specific features, like trees, playgrounds, or the sound of the waves].”\\n\\n在这里的活动和经历：  \\n“During my time there, I would often [describe activities you did, such as playing games, exploring nature, or spending time with family].”  \\n提供一个难忘的故事：  \\n“One unforgettable experience was when [describe a specific event or moment that happened there].”\\n\\n情感上的联系：  \\n“This place was significant to me because [explain why it holds a special place in your heart, such as creating lasting memories or a sense of comfort].”  \\n反思学到的教训：  \\n“I believe that my experiences there taught me [mention any insights or values, like the importance of friendship or appreciating nature].”\\n\\n结论：  \\n“In conclusion, the place I loved as a child remains etched in my memory for its [summarize key aspects like joy and adventure].”  \\n最后的想法：  \\n“Visiting such places from our past often reminds us of [what it symbolizes or how it shaped you].”\",\"titleTranslate\":\"告诉我一个你年轻时喜欢的地方。\"}",
  "openTime": "2025-02-24T16:02:57.000Z",
  "image_url": null
}