{
  "id": 69918,
  "key": "e",
  "difficulty": "2",
  "md5": null,
  "answer": "Oh, that's a great question! Honestly, I've been dreaming about taking a trip to Japan for quite some time now. The culture, the food, and just the overall vibe of the country really fascinate me. I can just imagine wandering through the bustling streets of Tokyo, soaking in the bright neon lights and, of course, indulging in some authentic sushi. \n\nI’d love to explore the temples in Kyoto too, you know, those stunning old buildings that are so rich in history. It’s like stepping back in time! Plus, I’ve heard the cherry blossoms are absolutely breathtaking in the spring, which would be a perfect backdrop for some amazing photos.\n\nAnd then there’s the countryside, which is totally different from the city life. I’d enjoy hiking in the mountains or maybe even soaking in an onsen, which just sounds super relaxing. Overall, I think this trip would be a fantastic mix of adventure and serenity. I can’t wait to experience all the unique aspects of Japanese culture firsthand. So yeah, that’s definitely a trip that’s high on my bucket list!",
  "title": "Tell me about a trip you would like to go on.",
  "extData": "{\"pronuncFile\":\"/20250327/3fe1e20a87d54c2490e8b9be38fc2c23.mp3\",\"answerTemplate\":\"开场陈述：  \\n“One trip that I would really love to go on is [destination or type of place, such as a tropical island, ancient city, etc.].”\\n\\n正文：  \\n关于目的地的描述：  \\n“I am particularly drawn to [specific features of the destination, such as its natural beauty, cultural heritage, or adventure opportunities] because [reason, such as wanting to experience new cultures or relax in nature].”\\n\\n计划的活动：  \\n“While I’m there, I would like to [list activities, such as explore historical sites, try local cuisine, relax on the beach, etc.], so that I can [reason, such as learn more about the local culture or enjoy some downtime].”  \\n进一步说明：  \\n“Additionally, I am excited about [specific attractions or activities, such as hiking a famous trail, visiting museums, or participating in local festivals] because [reason for interest].”\\n\\n结论：  \\n总结这次旅行的意义：  \\n“In conclusion, this trip to [destination] represents an opportunity to [summarize the benefits and personal significance, like broaden my perspective, unwind, or connect with nature].”  \\n最后的想法：  \\n“I believe it would be an unforgettable experience that I would cherish for years to come.”\",\"titleTranslate\":\"告诉我一个你想去的旅行。\"}",
  "openTime": "2025-03-27T04:01:54.000Z",
  "image_url": null
}