{
  "id": 20551,
  "key": "e",
  "difficulty": "1",
  "md5": null,
  "answer": "Oh, okay, so in my community, there’s this store called “The Corner Market”, and it’s super popular, like, everyone knows about it. I think the reason people really like it is because it has this nice, friendly vibe, you know? The staff are super welcoming, and it feels like a place where you can just, like, chat with neighbors while shopping. \n\nThey offer a mix of things—like fresh groceries, baked goods, and even some locally made products, which is pretty cool. Also, they sometimes host small events, like tastings or workshops, and that kind of makes it more than just a regular store. Honestly, I feel like people keep going back because it’s convenient, but also because it feels like a little hub for the community.",
  "title": "Talk about a popular store or business in your community.\nWhat is the store called?\nWhy do people like it?\nWhat products or services does it offer?",
  "extData": "{\"pronuncFile\":\"/20250414/860ff6f13f3d44b2bfa0b1492efef36c.mp3\",\"answerTemplate\":\"1. Opening\\n   - \\\"Okay, let me tell you about [Store/Business Name].\\\"  \\n   - \\\"You know, it's pretty popular around here for a reason.\\\"  \\n\\n2.Body 1 (Reason/Example) \\n   - \\\"One reason people really like it is [Reason 1], like [Specific Example].\\\"  \\n   - \\\"For example, it's known for [Example or Key Feature].\\\"  \\n\\n3. Body 2 (Reason/Elaboration)  \\n   - \\\"Another thing that makes it stand out is [Reason 2].\\\"  \\n   - \\\"I mean, not many places offer [Service/Product/Characteristic] like this.\\\"  \\n   - \\\"Plus, it’s super convenient because [Additional Context].\\\"  \\n\\n4. Conclusion \\n   - \\\"So yeah, overall, [Store/Business Name] is definitely one of the favorites around here.\\\"  \\n   - \\\"It’s great because [Concluding Thought].\\\"  \"}",
  "openTime": "2025-09-26T13:38:09.000Z",
  "image_url": null
}